namelist_python/__init__.py
namelist_python/namelist.py
namelist_python/namelist_python.py
namelist_python/utils.py
namelist_python-0.1.4.dist-info/METADATA
namelist_python-0.1.4.dist-info/RECORD
namelist_python-0.1.4.dist-info/WHEEL
namelist_python-0.1.4.dist-info/top_level.txt
