Metadata-Version: 2.1
Name: namelist-python
Version: 0.1.4
Summary: Fortran namelist file parser in Python
Home-page: https://github.com/leifdenby/namelist_python
Author: Leif Denby
Author-email: leifdenby@gmail.com
License: UNKNOWN
Download-URL: https://github.com/leifdenby/namelist_python/archive/0.1.3.tar.gz
Keywords: namelist,fortran,parsing
Platform: UNKNOWN
